freshsales/__init__.py
freshsales/api.py
freshsales/errors.py
freshsales/exceptions.py
freshsales/models.py
freshsales/tests/__init__.py
freshsales/tests/conftest.py
freshsales/tests/test_accounts.py
freshsales/tests/test_appointments.py
freshsales/tests/test_contacts.py
freshsales/tests/test_deals.py
freshsales/tests/test_documents.py
freshsales/tests/test_lists.py
freshsales/tests/test_notes.py
freshsales/tests/test_products.py
freshsales/tests/test_sales_activities.py
freshsales/tests/test_search.py
freshsales/tests/test_selectors.py
freshsales/tests/test_tasks.py
freshsales/v2/__init__.py
freshsales/v2/api.py
freshsales/v2/errors.py
freshsales/v2/models.py
freshsales/v2/tests/__init__.py
freshsales/v2/tests/conftest.py
freshsales/v2/tests/test_accounts.py
freshsales/v2/tests/test_appointments.py
freshsales/v2/tests/test_contacts.py
freshsales/v2/tests/test_deals.py
freshsales/v2/tests/test_documents.py
freshsales/v2/tests/test_lists.py
freshsales/v2/tests/test_notes.py
freshsales/v2/tests/test_products.py
freshsales/v2/tests/test_sales_activities.py
freshsales/v2/tests/test_selectors.py
freshsales/v2/tests/test_tasks.py
python_freshworks_crm-1.1.2.dist-info/LICENSE
python_freshworks_crm-1.1.2.dist-info/METADATA
python_freshworks_crm-1.1.2.dist-info/WHEEL
python_freshworks_crm-1.1.2.dist-info/top_level.txt
python_freshworks_crm-1.1.2.dist-info/RECORD
